awslabs/__init__.py
awslabs/ec2_mcp_server/__init__.py
awslabs/ec2_mcp_server/aws_client.py
awslabs/ec2_mcp_server/errors.py
awslabs/ec2_mcp_server/models.py
awslabs/ec2_mcp_server/server.py
awslabs/ec2_mcp_server/modules/__init__.py
awslabs/ec2_mcp_server/modules/amis.py
awslabs/ec2_mcp_server/modules/instances.py
awslabs/ec2_mcp_server/modules/key_pairs.py
awslabs/ec2_mcp_server/modules/security_groups.py
awslabs/ec2_mcp_server/modules/snapshots.py
awslabs/ec2_mcp_server/modules/volumes.py
awslabs/ec2_mcp_server/modules/vpc_management.py
awslabs/ec2_mcp_server/utils/__init__.py
awslabs/ec2_mcp_server/utils/aws.py
awslabs/ec2_mcp_server/utils/config.py
awslabs/ec2_mcp_server/utils/key_storage.py
awslabs/ec2_mcp_server/utils/security.py
awslabs_ec2_mcp_server-0.1.2.dist-info/METADATA
awslabs_ec2_mcp_server-0.1.2.dist-info/WHEEL
awslabs_ec2_mcp_server-0.1.2.dist-info/entry_points.txt
awslabs_ec2_mcp_server-0.1.2.dist-info/licenses/LICENSE
awslabs_ec2_mcp_server-0.1.2.dist-info/licenses/NOTICE
awslabs_ec2_mcp_server-0.1.2.dist-info/RECORD
